ordeq_faiss/__init__.py
ordeq_faiss/_version.py
ordeq_faiss/index.py
ordeq_faiss/py.typed
ordeq_faiss-1.0.2.dist-info/licenses/LICENSE
ordeq_faiss-1.0.2.dist-info/METADATA
ordeq_faiss-1.0.2.dist-info/WHEEL
ordeq_faiss-1.0.2.dist-info/top_level.txt
ordeq_faiss-1.0.2.dist-info/RECORD
