Metadata-Version: 2.4
Name: ordeq_faiss
Version: 1.0.2
Summary: Faiss integration for Ordeq
Author: Niels Neerhoff, Simon Brugman
Maintainer: Niels Neerhoff, Simon Brugman
License-Expression: MIT
Requires-Python: >=3.10
License-File: LICENSE
Requires-Dist: ordeq>=1.2.0
Requires-Dist: faiss-cpu
Dynamic: license-file
